digitalmarketplace_developer_tools-2.0.0.dist-info/licenses/LICENCE
dmdevtools/__init__.py
dmdevtools/invoke_tasks.py
digitalmarketplace_developer_tools-2.0.0.dist-info/METADATA
digitalmarketplace_developer_tools-2.0.0.dist-info/WHEEL
digitalmarketplace_developer_tools-2.0.0.dist-info/top_level.txt
digitalmarketplace_developer_tools-2.0.0.dist-info/RECORD
