Metadata-Version: 2.4
Name: digitalmarketplace-developer-tools
Version: 2.0.0
Summary: Common developer tools for Digital Marketplace repos
Author: GDS Developers, CCS Developers
Project-URL: Homepage, https://github.com/Crown-Commercial-Service/digitalmarketplace-developer-tools
Project-URL: Repository, https://github.com/Crown-Commercial-Service/digitalmarketplace-developer-tools.git
Project-URL: Issues, https://github.com/Crown-Commercial-Service/digitalmarketplace-developer-tools/issues
Project-URL: Changelog, https://github.com/Crown-Commercial-Service/digitalmarketplace-developer-tools/CHANGELOG.md
Requires-Python: <3.15,>=3.9
License-File: LICENCE
Requires-Dist: colored>=2
Requires-Dist: invoke>=2
Provides-Extra: dev
Requires-Dist: ruff==0.14.13; extra == "dev"
Requires-Dist: invoke==2.2.1; extra == "dev"
Requires-Dist: mypy==1.19.1; extra == "dev"
Requires-Dist: pytest==8.4.2; extra == "dev"
Requires-Dist: pre-commit==4.3.0; extra == "dev"
Dynamic: license-file
